jlq_mcp_calculate/__init__.py
jlq_mcp_calculate/server.py
jlq_mcp_calculate-0.2.2.dist-info/WHEEL
jlq_mcp_calculate-0.2.2.dist-info/entry_points.txt
jlq_mcp_calculate-0.2.2.dist-info/METADATA
jlq_mcp_calculate-0.2.2.dist-info/RECORD
